README.md
setup.py
pulumi_yandex/__init__.py
pulumi_yandex/_inputs.py
pulumi_yandex/_utilities.py
pulumi_yandex/alb_backend_group.py
pulumi_yandex/alb_http_router.py
pulumi_yandex/alb_load_balancer.py
pulumi_yandex/alb_target_group.py
pulumi_yandex/alb_virtual_host.py
pulumi_yandex/api_gateway.py
pulumi_yandex/cdn_origin_group.py
pulumi_yandex/cdn_resource.py
pulumi_yandex/compute_disk.py
pulumi_yandex/compute_disk_placement_group.py
pulumi_yandex/compute_image.py
pulumi_yandex/compute_instance.py
pulumi_yandex/compute_instance_group.py
pulumi_yandex/compute_placement_group.py
pulumi_yandex/compute_snapshot.py
pulumi_yandex/container_registry.py
pulumi_yandex/container_registry_iam_binding.py
pulumi_yandex/container_repository.py
pulumi_yandex/container_repository_iam_binding.py
pulumi_yandex/dataproc_cluster.py
pulumi_yandex/datatransfer_endpoint.py
pulumi_yandex/datatransfer_transfer.py
pulumi_yandex/dns_record_set.py
pulumi_yandex/dns_zone.py
pulumi_yandex/function.py
pulumi_yandex/function_iam_binding.py
pulumi_yandex/function_scaling_policy.py
pulumi_yandex/function_trigger.py
pulumi_yandex/get_alb_backend_group.py
pulumi_yandex/get_alb_http_router.py
pulumi_yandex/get_alb_load_balancer.py
pulumi_yandex/get_alb_target_group.py
pulumi_yandex/get_alb_virtual_host.py
pulumi_yandex/get_api_gateway.py
pulumi_yandex/get_cdn_origin_group.py
pulumi_yandex/get_cdn_resource.py
pulumi_yandex/get_client_config.py
pulumi_yandex/get_compute_disk.py
pulumi_yandex/get_compute_disk_placement_group.py
pulumi_yandex/get_compute_image.py
pulumi_yandex/get_compute_instance.py
pulumi_yandex/get_compute_instance_group.py
pulumi_yandex/get_compute_placement_group.py
pulumi_yandex/get_compute_snapshot.py
pulumi_yandex/get_container_registry.py
pulumi_yandex/get_container_repository.py
pulumi_yandex/get_dataproc_cluster.py
pulumi_yandex/get_dns_zone.py
pulumi_yandex/get_function.py
pulumi_yandex/get_function_scaling_policy.py
pulumi_yandex/get_function_trigger.py
pulumi_yandex.egg-info/PKG-INFO
pulumi_yandex.egg-info/SOURCES.txt
pulumi_yandex.egg-info/dependency_links.txt
pulumi_yandex.egg-info/not-zip-safe
pulumi_yandex.egg-info/requires.txt
pulumi_yandex.egg-info/top_level.txt
