Metadata-Version: 2.1
Name: pulumi-yandex
Version: 0.12.0
Summary: A Pulumi package for creating and managing yandex cloud resources.
Home-page: https://pulumi.io
License: Apache-2.0
Project-URL: Repository, https://github.com/pulumi/pulumi-yandex
Keywords: pulumi yandex
Platform: UNKNOWN
